{
  "run_id": "20260319T230952",
  "config_path": ".auto-flow/pipeline.yaml",
  "started_at": "2026-03-19T23:09:52.629Z",
  "status": "running",
  "args": {},
  "env": {},
  "nodes": {
    "specification": {
      "status": "completed",
      "started_at": "2026-03-19T23:09:52.641Z",
      "session_id": "1b0bf723-d52c-40e2-908c-97b25acad628",
      "continuations": 0,
      "completed_at": "2026-03-19T23:13:00.652Z",
      "duration_ms": 188011,
      "cost_usd": 0.7306852499999998,
      "result": "Done. Summary: | - Selected issue **#157** (sdlc scope): \"Remove shared-rules read instruction from SKILL.md files (ADR-001 C2 Phase 2)\" | - Added **FR-S39** to `documents/requirements-sdlc.md` (section 3.39) with 4 acceptance criteria; Appendix C updated."
    },
    "design": {
      "status": "completed",
      "started_at": "2026-03-19T23:13:00.658Z",
      "session_id": "7d8e294f-1f63-4582-a101-091355d77b50",
      "continuations": 0,
      "completed_at": "2026-03-19T23:15:03.453Z",
      "duration_ms": 122795,
      "cost_usd": 0.47622849999999994,
      "result": "I produced `02-plan.md` with 3 variants: | - **Variant A (recommended, effort S):** Remove only the `# BEFORE YOU DO ANYTHING` heading + shared-rules read instruction (lines 7-11). Keep \"first tool call MUST be\" instructions as standalone paragraphs. Smallest blast radius, preserves useful agent-specific guidance. | - **Variant B (effort S):** Remove the entire block including first-tool-call inst"
    },
    "decision": {
      "status": "completed",
      "started_at": "2026-03-19T23:15:03.455Z",
      "session_id": "c587db2a-d953-408c-a736-49468f2bb169",
      "continuations": 0,
      "completed_at": "2026-03-19T23:17:14.348Z",
      "duration_ms": 130893,
      "cost_usd": 0.723985,
      "result": "Done. I selected **Variant A**, produced the task breakdown in `03-decision.md`, updated SDS §3.4 with FR-S39 details, created branch `sdlc/issue-157`, and opened draft PR #171. Issue #157 commented."
    },
    "implementation": {
      "status": "completed",
      "started_at": "2026-03-19T23:17:14.350Z",
      "iteration": 2,
      "completed_at": "2026-03-19T23:29:48.095Z",
      "duration_ms": 753745
    },
    "build": {
      "status": "completed",
      "started_at": "2026-03-19T23:23:35.696Z",
      "completed_at": "2026-03-19T23:25:52.144Z",
      "duration_ms": 136448,
      "cost_usd": 0.7504255,
      "result": "Done. I added section 3.39 (FR-S39) to `documents/requirements-sdlc.md` with description, dep reference, and 4 acceptance criteria, plus the Appendix C row. `deno task check` passes (533 tests). Committed and pushed."
    },
    "verify": {
      "status": "completed",
      "started_at": "2026-03-19T23:25:52.146Z",
      "completed_at": "2026-03-19T23:29:48.077Z",
      "duration_ms": 235931,
      "cost_usd": 0.8803522500000001,
      "result": "**QA verdict: PASS** | - **Check**: 533 tests, 0 failures — all 10 check stages passed | - **FR-S39**: confirmed at §3.39 (line 881) + Appendix C (line 1028) in `requirements-sdlc.md` — blocking issue from iteration 1 resolved"
    },
    "tech-lead-review": {
      "status": "running",
      "started_at": "2026-03-19T23:29:48.104Z"
    }
  },
  "total_cost_usd": 3.5616765
}
